<?xml version="1.0" encoding="iso-8859-1" ?>
<newsitem itemid="132611" id="root" date="1996-10-22" xml:lang="en">
<title>USA: Universal Corp Q1 shr rises to $0.57.</title>
<headline>Universal Corp Q1 shr rises to $0.57.</headline>
<dateline>RICHMOND, Va. 1996-10-22</dateline>
<text>
<p>Periods ended Sept 30.</p>
<p>		(Dollars in thousands, except per-share amounts)</p>
<p>							  1996	  1995</p>
<p> Sales and other operating revenues	$820,840    $842,454</p>
<p> Net income					  20,022	10,189</p>
<p> Earnings per common share			  .57	   .29</p>
<p> Cash dividends declared			   .255	   .25</p>
<p> Average common shares outstanding     35,056,357  35,030,314</p>
<p>NOTE: Universal Corp's operations are seasonal; therefore, the results of operations for Q1 are not necessarily indicative of the full year.</p>
<p>Certain results for period ended Sept. 1995 have been reclassified to conform to current year presentation.</p>
<p>-- New York Newsdesk 212 859-1610</p>
</text>
<copyright>(c) Reuters Limited 1996</copyright>
<metadata>
<codes class="bip:countries:1.0">
  <code code="USA">
    <editdetail attribution="Reuters BIP Coding Group" action="confirmed" date="1996-10-22"/>
  </code>
</codes>
<codes class="bip:industries:1.0">
  <code code="I61000">
    <editdetail attribution="Reuters BIP Coding Group" action="confirmed" date="1996-10-22"/>
  </code>
</codes>
<codes class="bip:topics:1.0">
  <code code="C15">
    <editdetail attribution="Reuters BIP Coding Group" action="confirmed" date="1996-10-22"/>
  </code>
  <code code="C151">
    <editdetail attribution="Reuters BIP Coding Group" action="confirmed" date="1996-10-22"/>
  </code>
  <code code="CCAT">
    <editdetail attribution="Reuters BIP Coding Group" action="confirmed" date="1996-10-22"/>
  </code>
</codes>
<dc element="dc.date.created" value="1996-10-22"/>
<dc element="dc.publisher" value="Reuters Holdings Plc"/>
<dc element="dc.date.published" value="1996-10-22"/>
<dc element="dc.source" value="Reuters"/>
<dc element="dc.creator.location" value="RICHMOND, Va."/>
<dc element="dc.creator.location.country.name" value="USA"/>
<dc element="dc.source" value="Reuters"/>
</metadata>
</newsitem>
