<?xml version="1.0" encoding="iso-8859-1" ?>
<newsitem itemid="134223" id="root" date="1996-10-22" xml:lang="en">
<title>INDIA: India broker recommendations for BSE's top stocks.</title>
<headline>India broker recommendations for BSE's top stocks.</headline>
<dateline>BOMBAY 1996-10-22</dateline>
<text>
<p>The following are the latest recommendations from eight top Indian securities firms on stocks which make up the benchmark index of the Bombay Stock Exchange.</p>
<p> COMPANY  NAME OF BROKER/RECOMMENDATION</p>
<p>	  HG  JM  KS  SSKI  DB  ISEC  JCBK  PC</p>
<p> ACC     S   H   H    B    H    H     H    S</p>
<p> Arvind  B   H   H    B    H    H     H    S</p>
<p> Bajaj   B   H   H    B    H    H     B    B</p>
<p> BHEL    B   B   H    B    B    H     H    B</p>
<p> BSES    B   B   H    -    H    -     B    B</p>
<p> Colgate -   H   -    -    B    H     H    S</p>
<p> G E Ship -  H   H    B    S    -     H    S</p>
<p> Glaxo   B   H   H    -    H    B     H    B</p>
<p> Grasim  -   H   -    B    S    H     H    S</p>
<p> Guj Amb B   B   B    B    B    H     H    S</p>
<p> Hindalco H  H*  H    B    H    B     H    B</p>
<p> HLL     B   H   -    S    H    B     B    B</p>
<p> HPCL    B   H   H    B    B    B     B    B</p>
<p> ICICI   B   H   -    B    H    -     H    H</p>
<p> IDBI    B   H   -    B    H    -     B    H</p>
<p> Ind Hot B   H   H    B    H    B     B    B</p>
<p> IPCL    S   H*  H    B    H    H     S    B</p>
<p> ITC     H   H   -    B    H    -     H    S</p>
<p> L &amp; T   B   B   -    B    B    H     H    B</p>
<p> M&amp;M     B   B   B    B    B    B     B    B</p>
<p> MTNL    B   B   B    B    B    B     B    S</p>
<p> Nestle  -   H   -    -    H    S     H    H</p>
<p> Ranbaxy B   H*  H    B    H    B     S    H</p>
<p> Reliance S  S   -    B    H    S     H    S</p>
<p> SAIL    S   S   H    S    H    S     S    S</p>
<p> SBI     B   B   -    B    B    H     B    B</p>
<p> Tata Che -  H   -    -    S    S     H    H</p>
<p> Tata Pow B  B   H    -    H    B     B    B</p>
<p> TELCO   B   B   B    B    B    B     B    B</p>
<p> TISCO   S   H** H    S    S    S     S    S</p>
<p>RECOMMENDATIONS: B =BUY, S =SELL, H=HOLD</p>
<p>BROKERS:	HG - H.G. Asia Ltd.</p>
<p>		  JM - J.M. Share &amp; Stock Brokers Ltd.</p>
<p>		  KS - Kotak Securities</p>
<p>		SSKI - SSKI Securities</p>
<p>		  DB - Dalal &amp; Broacha</p>
<p>		ISEC - ICICI Securities</p>
<p>		JCBK - James Capel Batlivala &amp; Karani</p>
<p>		  PC - Peregrine Capital India</p>
<p>NOTE :  * At least one year,  ** Long Term - 2 years</p>
<p>To add to this table please call Priya Ramani or Amiti Kripalani at +91-22-265-9000 or fax recommendations to 264 1699</p>
<p>-- Bombay newsroom +91-22-265 9000</p>
</text>
<copyright>(c) Reuters Limited 1996</copyright>
<metadata>
<codes class="bip:countries:1.0">
  <code code="INDIA">
    <editdetail attribution="Reuters BIP Coding Group" action="confirmed" date="1996-10-22"/>
  </code>
</codes>
<codes class="bip:industries:1.0">
  <code code="I14000">
    <editdetail attribution="Reuters BIP Coding Group" action="confirmed" date="1996-10-22"/>
  </code>
  <code code="I16100">
    <editdetail attribution="Reuters BIP Coding Group" action="confirmed" date="1996-10-22"/>
  </code>
  <code code="I22450">
    <editdetail attribution="Reuters BIP Coding Group" action="confirmed" date="1996-10-22"/>
  </code>
  <code code="I24200">
    <editdetail attribution="Reuters BIP Coding Group" action="confirmed" date="1996-10-22"/>
  </code>
  <code code="I25120">
    <editdetail attribution="Reuters BIP Coding Group" action="confirmed" date="1996-10-22"/>
  </code>
  <code code="I25700">
    <editdetail attribution="Reuters BIP Coding Group" action="confirmed" date="1996-10-22"/>
  </code>
  <code code="I25800">
    <editdetail attribution="Reuters BIP Coding Group" action="confirmed" date="1996-10-22"/>
  </code>
  <code code="I26000">
    <editdetail attribution="Reuters BIP Coding Group" action="confirmed" date="1996-10-22"/>
  </code>
  <code code="I32000">
    <editdetail attribution="Reuters BIP Coding Group" action="confirmed" date="1996-10-22"/>
  </code>
  <code code="I34200">
    <editdetail attribution="Reuters BIP Coding Group" action="confirmed" date="1996-10-22"/>
  </code>
  <code code="I35102">
    <editdetail attribution="Reuters BIP Coding Group" action="confirmed" date="1996-10-22"/>
  </code>
  <code code="I36300">
    <editdetail attribution="Reuters BIP Coding Group" action="confirmed" date="1996-10-22"/>
  </code>
  <code code="I41000">
    <editdetail attribution="Reuters BIP Coding Group" action="confirmed" date="1996-10-22"/>
  </code>
  <code code="I42900">
    <editdetail attribution="Reuters BIP Coding Group" action="confirmed" date="1996-10-22"/>
  </code>
  <code code="I43000">
    <editdetail attribution="Reuters BIP Coding Group" action="confirmed" date="1996-10-22"/>
  </code>
  <code code="I66500">
    <editdetail attribution="Reuters BIP Coding Group" action="confirmed" date="1996-10-22"/>
  </code>
  <code code="I74000">
    <editdetail attribution="Reuters BIP Coding Group" action="confirmed" date="1996-10-22"/>
  </code>
  <code code="I81501">
    <editdetail attribution="Reuters BIP Coding Group" action="confirmed" date="1996-10-22"/>
  </code>
  <code code="I8150106">
    <editdetail attribution="Reuters BIP Coding Group" action="confirmed" date="1996-10-22"/>
  </code>
</codes>
<codes class="bip:topics:1.0">
  <code code="C15">
    <editdetail attribution="Reuters BIP Coding Group" action="confirmed" date="1996-10-22"/>
  </code>
  <code code="C152">
    <editdetail attribution="Reuters BIP Coding Group" action="confirmed" date="1996-10-22"/>
  </code>
  <code code="CCAT">
    <editdetail attribution="Reuters BIP Coding Group" action="confirmed" date="1996-10-22"/>
  </code>
</codes>
<dc element="dc.date.created" value="1996-10-22"/>
<dc element="dc.publisher" value="Reuters Holdings Plc"/>
<dc element="dc.date.published" value="1996-10-22"/>
<dc element="dc.source" value="Reuters"/>
<dc element="dc.creator.location" value="BOMBAY"/>
<dc element="dc.creator.location.country.name" value="INDIA"/>
<dc element="dc.source" value="Reuters"/>
</metadata>
</newsitem>
