<?xml version="1.0" encoding="iso-8859-1" ?>
<newsitem itemid="136387" id="root" date="1996-10-23" xml:lang="en">
<title>SOUTH AFRICA: RMB executive to head S.Africa stock market.</title>
<headline>RMB executive to head S.Africa stock market.</headline>
<dateline>JOHANNESBURG 1996-10-23</dateline>
<text>
<p>The Johannesburg Stock Exchange on Wednesday named Russell Loubser, executive director in charge of financial markets at Rand Merchant Bank, as its new executive president.</p>
<p>Loubser will take over from Roy Andersen who steps down in January 1997, the exchange said in a statement.  </p>
<p>Loubser, 46, helped to develop the South African futures market and was chairman of the South African Futures Exchange for two years and deputy chairman for one.</p>
<p>He will take over full responsibilties from Andersen from the beginning of February.</p>
<p>-- Johannesburg newsroom +27 11 482 1003</p>
</text>
<copyright>(c) Reuters Limited 1996</copyright>
<metadata>
<codes class="bip:countries:1.0">
  <code code="SAFR">
    <editdetail attribution="Reuters BIP Coding Group" action="confirmed" date="1996-10-23"/>
  </code>
</codes>
<codes class="bip:industries:1.0">
  <code code="I83100">
    <editdetail attribution="Reuters BIP Coding Group" action="confirmed" date="1996-10-23"/>
  </code>
</codes>
<codes class="bip:topics:1.0">
  <code code="C41">
    <editdetail attribution="Reuters BIP Coding Group" action="confirmed" date="1996-10-23"/>
  </code>
  <code code="C411">
    <editdetail attribution="Reuters BIP Coding Group" action="confirmed" date="1996-10-23"/>
  </code>
  <code code="CCAT">
    <editdetail attribution="Reuters BIP Coding Group" action="confirmed" date="1996-10-23"/>
  </code>
  <code code="M11">
    <editdetail attribution="Reuters BIP Coding Group" action="confirmed" date="1996-10-23"/>
  </code>
  <code code="MCAT">
    <editdetail attribution="Reuters BIP Coding Group" action="confirmed" date="1996-10-23"/>
  </code>
</codes>
<dc element="dc.date.created" value="1996-10-23"/>
<dc element="dc.publisher" value="Reuters Holdings Plc"/>
<dc element="dc.date.published" value="1996-10-23"/>
<dc element="dc.source" value="Reuters"/>
<dc element="dc.creator.location" value="JOHANNESBURG"/>
<dc element="dc.creator.location.country.name" value="SOUTH AFRICA"/>
<dc element="dc.source" value="Reuters"/>
</metadata>
</newsitem>
